tokenometry/__init__.py
tokenometry/core.py
tokenometry-1.0.7.dist-info/licenses/LICENSE
tokenometry-1.0.7.dist-info/METADATA
tokenometry-1.0.7.dist-info/WHEEL
tokenometry-1.0.7.dist-info/top_level.txt
tokenometry-1.0.7.dist-info/RECORD
