Metadata-Version: 2.4
Name: tokenometry
Version: 1.0.7
Summary: A sophisticated multi-strategy crypto analysis bot for trading signals
Author-email: nguyenph88 <your.email@example.com>
Maintainer-email: nguyenph88 <your.email@example.com>
License: MIT
Project-URL: Homepage, https://github.com/nguyenph88/Tokenometry
Project-URL: Documentation, https://github.com/nguyenph88/Tokenometry#readme
Project-URL: Repository, https://github.com/nguyenph88/Tokenometry
Project-URL: Issues, https://github.com/nguyenph88/Tokenometry/issues
Project-URL: Changelog, https://github.com/nguyenph88/Tokenometry/blob/main/CHANGELOG.md
Keywords: cryptocurrency,trading,analysis,bot,signals,technical-analysis,crypto,bitcoin,ethereum
Classifier: Development Status :: 4 - Beta
Classifier: Intended Audience :: Financial and Insurance Industry
Classifier: Intended Audience :: Developers
Classifier: Operating System :: OS Independent
Classifier: Programming Language :: Python :: 3
Classifier: Programming Language :: Python :: 3.8
Classifier: Programming Language :: Python :: 3.9
Classifier: Programming Language :: Python :: 3.10
Classifier: Programming Language :: Python :: 3.11
Classifier: Programming Language :: Python :: 3.12
Classifier: Programming Language :: Python :: 3.13
Classifier: Topic :: Office/Business :: Financial :: Investment
Classifier: Topic :: Scientific/Engineering :: Information Analysis
Classifier: Topic :: Software Development :: Libraries :: Python Modules
Classifier: License :: OSI Approved :: MIT License
Requires-Python: >=3.8
License-File: LICENSE
Requires-Dist: coinbase-advanced-py>=0.5.0
Requires-Dist: pandas>=2.1.0
Requires-Dist: numpy<2.0.0,>=1.24.0
Requires-Dist: matplotlib>=3.7.0
Requires-Dist: python-dotenv>=1.0.0
Requires-Dist: requests>=2.31.0
Requires-Dist: cryptography>=42.0.4
Requires-Dist: PyJWT>=2.8.0
Requires-Dist: websockets<14.0,>=12.0
Requires-Dist: backoff>=2.2.1
Requires-Dist: build>=1.0.0
Provides-Extra: dev
Requires-Dist: pytest>=7.4.0; extra == "dev"
Requires-Dist: pytest-cov>=4.1.0; extra == "dev"
Requires-Dist: black>=23.0.0; extra == "dev"
Requires-Dist: flake8>=6.0.0; extra == "dev"
Requires-Dist: mypy>=1.5.0; extra == "dev"
Requires-Dist: twine>=4.0.0; extra == "dev"
Requires-Dist: build>=1.0.0; extra == "dev"
Dynamic: license-file
